switchbot_mqtt/__init__.py
switchbot_mqtt/_cli.py
switchbot_mqtt/_utils.py
switchbot_mqtt/_actors/__init__.py
switchbot_mqtt/_actors/base.py
switchbot_mqtt-3.3.1.dist-info/COPYING
switchbot_mqtt-3.3.1.dist-info/METADATA
switchbot_mqtt-3.3.1.dist-info/WHEEL
switchbot_mqtt-3.3.1.dist-info/entry_points.txt
switchbot_mqtt-3.3.1.dist-info/top_level.txt
switchbot_mqtt-3.3.1.dist-info/RECORD
