Metadata-Version: 2.1
Name: switchbot-mqtt
Version: 3.3.1
Summary: MQTT client controlling SwitchBot button & curtain automators, compatible with home-assistant.io's MQTT Switch & Cover platform
Home-page: https://github.com/fphammerle/switchbot-mqtt
Author: Fabian Peter Hammerle
Author-email: fabian@hammerle.me
License: GPLv3+
Project-URL: Changelog, https://github.com/fphammerle/switchbot-mqtt/blob/master/CHANGELOG.md
Keywords: IoT,automation,bluetooth,button,click,cover,curtain,home-assistant.io,home-automation,mqtt,press,push,switchbot
Platform: UNKNOWN
Classifier: Development Status :: 3 - Alpha
Classifier: Intended Audience :: End Users/Desktop
Classifier: Intended Audience :: System Administrators
Classifier: License :: OSI Approved :: GNU General Public License v3 or later (GPLv3+)
Classifier: Operating System :: POSIX :: Linux
Classifier: Programming Language :: Python :: 3.7
Classifier: Programming Language :: Python :: 3.8
Classifier: Programming Language :: Python :: 3.9
Classifier: Programming Language :: Python :: 3.10
Classifier: Topic :: Home Automation
Requires-Python: >=3.7
Requires-Dist: PySwitchbot (<0.13,>=0.10.0)
Requires-Dist: bluepy (<2,>=1.3.0)
Requires-Dist: paho-mqtt (<2)
